{
 "cells": [
  {
   "cell_type": "code",
   "execution_count": 1,
   "metadata": {},
   "outputs": [],
   "source": [
    "b = 9\n",
    "def func(a):\n",
    "    print(a)\n",
    "    print(b)\n",
    "    b = 6"
   ]
  },
  {
   "cell_type": "code",
   "execution_count": 2,
   "metadata": {},
   "outputs": [
    {
     "name": "stdout",
     "output_type": "stream",
     "text": [
      "1\n"
     ]
    },
    {
     "ename": "UnboundLocalError",
     "evalue": "local variable 'b' referenced before assignment",
     "output_type": "error",
     "traceback": [
      "\u001b[0;31m---------------------------------------------------------------------------\u001b[0m",
      "\u001b[0;31mUnboundLocalError\u001b[0m                         Traceback (most recent call last)",
      "\u001b[0;32m<ipython-input-2-9ed089a72395>\u001b[0m in \u001b[0;36m<module>\u001b[0;34m()\u001b[0m\n\u001b[0;32m----> 1\u001b[0;31m \u001b[0mfunc\u001b[0m\u001b[0;34m(\u001b[0m\u001b[0;36m1\u001b[0m\u001b[0;34m)\u001b[0m\u001b[0;34m\u001b[0m\u001b[0m\n\u001b[0m",
      "\u001b[0;32m<ipython-input-1-f8596bda3f04>\u001b[0m in \u001b[0;36mfunc\u001b[0;34m(a)\u001b[0m\n\u001b[1;32m      2\u001b[0m \u001b[0;32mdef\u001b[0m \u001b[0mfunc\u001b[0m\u001b[0;34m(\u001b[0m\u001b[0ma\u001b[0m\u001b[0;34m)\u001b[0m\u001b[0;34m:\u001b[0m\u001b[0;34m\u001b[0m\u001b[0m\n\u001b[1;32m      3\u001b[0m     \u001b[0mprint\u001b[0m\u001b[0;34m(\u001b[0m\u001b[0ma\u001b[0m\u001b[0;34m)\u001b[0m\u001b[0;34m\u001b[0m\u001b[0m\n\u001b[0;32m----> 4\u001b[0;31m     \u001b[0mprint\u001b[0m\u001b[0;34m(\u001b[0m\u001b[0mb\u001b[0m\u001b[0;34m)\u001b[0m\u001b[0;34m\u001b[0m\u001b[0m\n\u001b[0m\u001b[1;32m      5\u001b[0m     \u001b[0mb\u001b[0m \u001b[0;34m=\u001b[0m \u001b[0;36m6\u001b[0m\u001b[0;34m\u001b[0m\u001b[0m\n",
      "\u001b[0;31mUnboundLocalError\u001b[0m: local variable 'b' referenced before assignment"
     ]
    }
   ],
   "source": [
    "func(1)"
   ]
  },
  {
   "cell_type": "code",
   "execution_count": 3,
   "metadata": {},
   "outputs": [],
   "source": [
    "b = 9\n",
    "def func(a):\n",
    "    global b\n",
    "    print(a)\n",
    "    print(b)\n",
    "    b = 6"
   ]
  },
  {
   "cell_type": "code",
   "execution_count": 4,
   "metadata": {},
   "outputs": [
    {
     "name": "stdout",
     "output_type": "stream",
     "text": [
      "1\n",
      "9\n"
     ]
    }
   ],
   "source": [
    "func(1)"
   ]
  },
  {
   "cell_type": "code",
   "execution_count": 5,
   "metadata": {},
   "outputs": [
    {
     "name": "stdout",
     "output_type": "stream",
     "text": [
      "1\n",
      "6\n"
     ]
    }
   ],
   "source": [
    "func(1)"
   ]
  },
  {
   "cell_type": "code",
   "execution_count": 6,
   "metadata": {},
   "outputs": [],
   "source": [
    "from dis import dis"
   ]
  },
  {
   "cell_type": "code",
   "execution_count": 7,
   "metadata": {},
   "outputs": [
    {
     "name": "stdout",
     "output_type": "stream",
     "text": [
      "1\n",
      "6\n",
      "  3           0 LOAD_GLOBAL              0 (print)\n",
      "              2 LOAD_FAST                0 (a)\n",
      "              4 CALL_FUNCTION            1\n",
      "              6 POP_TOP\n",
      "\n",
      "  4           8 LOAD_GLOBAL              0 (print)\n",
      "    -->      10 LOAD_FAST                1 (b)\n",
      "             12 CALL_FUNCTION            1\n",
      "             14 POP_TOP\n",
      "\n",
      "  5          16 LOAD_CONST               1 (6)\n",
      "             18 STORE_FAST               1 (b)\n",
      "             20 LOAD_CONST               0 (None)\n",
      "             22 RETURN_VALUE\n"
     ]
    }
   ],
   "source": [
    "dis(func(1))"
   ]
  },
  {
   "cell_type": "code",
   "execution_count": 8,
   "metadata": {},
   "outputs": [
    {
     "name": "stdout",
     "output_type": "stream",
     "text": [
      "1\n",
      "6\n",
      "  3           0 LOAD_GLOBAL              0 (print)\n",
      "              2 LOAD_FAST                0 (a)\n",
      "              4 CALL_FUNCTION            1\n",
      "              6 POP_TOP\n",
      "\n",
      "  4           8 LOAD_GLOBAL              0 (print)\n",
      "    -->      10 LOAD_FAST                1 (b)\n",
      "             12 CALL_FUNCTION            1\n",
      "             14 POP_TOP\n",
      "\n",
      "  5          16 LOAD_CONST               1 (6)\n",
      "             18 STORE_FAST               1 (b)\n",
      "             20 LOAD_CONST               0 (None)\n",
      "             22 RETURN_VALUE\n"
     ]
    }
   ],
   "source": [
    "dis(func(1))"
   ]
  },
  {
   "cell_type": "code",
   "execution_count": null,
   "metadata": {},
   "outputs": [],
   "source": []
  }
 ],
 "metadata": {
  "kernelspec": {
   "display_name": "Python 3",
   "language": "python",
   "name": "python3"
  },
  "language_info": {
   "codemirror_mode": {
    "name": "ipython",
    "version": 3
   },
   "file_extension": ".py",
   "mimetype": "text/x-python",
   "name": "python",
   "nbconvert_exporter": "python",
   "pygments_lexer": "ipython3",
   "version": "3.6.1"
  }
 },
 "nbformat": 4,
 "nbformat_minor": 2
}
